voila_topbar/__init__.py
voila_topbar/_version.py
voila_topbar-0.1.1.data/data/share/jupyter/labextensions/voila_topbar/build_log.json
voila_topbar-0.1.1.data/data/share/jupyter/labextensions/voila_topbar/package.json
voila_topbar-0.1.1.data/data/share/jupyter/labextensions/voila_topbar/static/lib_index_js.0394783712e4a44bc7b5.js
voila_topbar-0.1.1.data/data/share/jupyter/labextensions/voila_topbar/static/lib_index_js.0394783712e4a44bc7b5.js.map
voila_topbar-0.1.1.data/data/share/jupyter/labextensions/voila_topbar/static/lib_index_js.0489f6fda15090847c60.js
voila_topbar-0.1.1.data/data/share/jupyter/labextensions/voila_topbar/static/lib_index_js.0489f6fda15090847c60.js.map
voila_topbar-0.1.1.data/data/share/jupyter/labextensions/voila_topbar/static/lib_index_js.1ec0e3ba66aed2244d43.js
voila_topbar-0.1.1.data/data/share/jupyter/labextensions/voila_topbar/static/lib_index_js.1ec0e3ba66aed2244d43.js.map
voila_topbar-0.1.1.data/data/share/jupyter/labextensions/voila_topbar/static/lib_index_js.33eb2cddc0c0f25e734a.js
voila_topbar-0.1.1.data/data/share/jupyter/labextensions/voila_topbar/static/lib_index_js.33eb2cddc0c0f25e734a.js.map
voila_topbar-0.1.1.data/data/share/jupyter/labextensions/voila_topbar/static/lib_index_js.369f0e85271e3077510c.js
voila_topbar-0.1.1.data/data/share/jupyter/labextensions/voila_topbar/static/lib_index_js.369f0e85271e3077510c.js.map
voila_topbar-0.1.1.data/data/share/jupyter/labextensions/voila_topbar/static/lib_index_js.3e1fec74df71a229d315.js
voila_topbar-0.1.1.data/data/share/jupyter/labextensions/voila_topbar/static/lib_index_js.3e1fec74df71a229d315.js.map
voila_topbar-0.1.1.data/data/share/jupyter/labextensions/voila_topbar/static/lib_index_js.3e70aed4037398d37d69.js
voila_topbar-0.1.1.data/data/share/jupyter/labextensions/voila_topbar/static/lib_index_js.3e70aed4037398d37d69.js.map
voila_topbar-0.1.1.data/data/share/jupyter/labextensions/voila_topbar/static/lib_index_js.403a7e4edc5a4656e218.js
voila_topbar-0.1.1.dist-info/METADATA
voila_topbar-0.1.1.dist-info/WHEEL
voila_topbar-0.1.1.dist-info/licenses/LICENSE
voila_topbar-0.1.1.dist-info/RECORD
