Metadata-Version: 2.1
Name: voila_topbar
Version: 0.1.1
Summary: A Voila extension
Project-URL: Homepage, https://github.com/voila-dashboards/voila-topbar
Project-URL: Bug Tracker, https://github.com/voila-dashboards/voila-topbar/issues
Project-URL: Repository, https://github.com/voila-dashboards/voila-topbar.git
Author: Voilà contributors
License: BSD 3-Clause License
License-File: LICENSE
Classifier: Framework :: Jupyter
Classifier: Framework :: Jupyter :: JupyterLab
Classifier: Framework :: Jupyter :: JupyterLab :: 4
Classifier: Framework :: Jupyter :: JupyterLab :: Extensions
Classifier: Framework :: Jupyter :: JupyterLab :: Extensions :: Prebuilt
Classifier: License :: OSI Approved :: BSD License
Classifier: Programming Language :: Python
Classifier: Programming Language :: Python :: 3
Classifier: Programming Language :: Python :: 3.8
Classifier: Programming Language :: Python :: 3.9
Classifier: Programming Language :: Python :: 3.10
Classifier: Programming Language :: Python :: 3.11
Requires-Python: >=3.8
